zc.lockfile-3.0.post1-py3.9-nspkg.pth
zc/lockfile/README.txt
zc/lockfile/__init__.py
zc/lockfile/tests.py
zc.lockfile-3.0.post1.dist-info/LICENSE.txt
zc.lockfile-3.0.post1.dist-info/METADATA
zc.lockfile-3.0.post1.dist-info/WHEEL
zc.lockfile-3.0.post1.dist-info/namespace_packages.txt
zc.lockfile-3.0.post1.dist-info/top_level.txt
zc.lockfile-3.0.post1.dist-info/RECORD
