Metadata-Version: 2.1
Name: zc.lockfile
Version: 3.0.post1
Summary: Basic inter-process locks
Home-page: https://github.com/zopefoundation/zc.lockfile
Author: Zope Foundation
Author-email: zope-dev@zope.dev
License: ZPL 2.1
Keywords: lock
Classifier: Development Status :: 5 - Production/Stable
Classifier: Intended Audience :: Developers
Classifier: License :: OSI Approved :: Zope Public License
Classifier: Natural Language :: English
Classifier: Operating System :: POSIX
Classifier: Operating System :: Microsoft :: Windows
Classifier: Programming Language :: Python
Classifier: Programming Language :: Python :: 3
Classifier: Programming Language :: Python :: 3.7
Classifier: Programming Language :: Python :: 3.8
Classifier: Programming Language :: Python :: 3.9
Classifier: Programming Language :: Python :: 3.10
Classifier: Programming Language :: Python :: 3.11
Classifier: Programming Language :: Python :: Implementation :: CPython
Classifier: Programming Language :: Python :: Implementation :: PyPy
Classifier: Topic :: Software Development
Requires-Python: >=3.7
Provides-Extra: test
License-File: LICENSE.txt
